[{"title":"Beaufort","author":"Raimondo Do","publishYear":2008},
{"title":"Green Fish (Chorok mulkogi)","author":"Lamont Pacey","publishYear":1999},
{"title":"Brief Interviews with Hideous Men","author":"Emlyn Dodman","publishYear":1994},
{"title":"Forever Amber","author":"Earlie Gentil","publishYear":2000},
{"title":"Knife in the Water (Nóz w wodzie)","author":"Ana Pechard","publishYear":1969},
{"title":"Donnie Darko","author":"Frederica Trathan","publishYear":1999},
{"title":"Dracula","author":"Debi Pieper","publishYear":1998},
{"title":"Baby-Sitters Club, The","author":"Marina Goad","publishYear":1995},
{"title":"Delphine 1, Yvan 0","author":"Harrison Pedrick","publishYear":2002},
{"title":"Ghost Son","author":"Crystie Breslin","publishYear":1995},
{"title":"Circle of Eight","author":"Kiele Noton","publishYear":2008},
{"title":"Kid With a Bike, The (Le gamin au vélo)","author":"Tobi Cosin","publishYear":1957},
{"title":"Stealing Beauty","author":"Augustin Advani","publishYear":2007},
{"title":"New Tale of Zatoichi (Shin Zatôichi monogatari) (Zatôichi 3)","author":"Bette-ann Overthrow","publishYear":1995},
{"title":"Steam: The Turkish Bath (Hamam)","author":"Porter Denisevich","publishYear":2003},
{"title":"Wolf","author":"Madella Confort","publishYear":2009},
{"title":"Boys Life","author":"Obadiah Delacroix","publishYear":1994},
{"title":"Any Given Sunday","author":"Vassili Testro","publishYear":2000},
{"title":"Leprechaun","author":"Corrie Westnage","publishYear":1994},
{"title":"Little Voice","author":"Karrah Escalante","publishYear":2010},
{"title":"Music of the Heart","author":"Yevette Colby","publishYear":1994},
{"title":"Fragments of an Alms-Film (Fragmentos de um Filme-Esmola: A Sagrada Família)","author":"Shirl Noell","publishYear":2010},
{"title":"Bummer (Bumer)","author":"Flint Salmoni","publishYear":2000},
{"title":"Martha Marcy May Marlene","author":"Francesco Burghall","publishYear":1999},
{"title":"Inuyasha the Movie: The Castle Beyond the Looking Glass","author":"Anatol Steer","publishYear":2008},
{"title":"Marathon Man","author":"Chelsy Petrus","publishYear":2002},
{"title":"Map of the Human Heart","author":"Frazier Gambell","publishYear":2000},
{"title":"Amy","author":"Marnie Paxman","publishYear":2003},
{"title":"Nobody Else But You (Poupoupidou)","author":"Trstram McCord","publishYear":1994},
{"title":"Cadillac Man","author":"Belinda Barraclough","publishYear":2011},
{"title":"Battle for Haditha","author":"Kimmy Chapelhow","publishYear":1996},
{"title":"Ivan Vasilievich: Back to the Future (Ivan Vasilievich menyaet professiyu)","author":"Vivianne Scotchmor","publishYear":1964},
{"title":"Beautiful Kate","author":"Jeanine Bacup","publishYear":1997},
{"title":"Couples Retreat","author":"Logan Sutherns","publishYear":2001},
{"title":"Waking Madison ","author":"Inglebert Klesl","publishYear":2008},
{"title":"Kautokeino Rebellion, The (Kautokeino-opprøret)","author":"Pepito Pember","publishYear":2010},
{"title":"Takva: A Man's Fear of God","author":"Boy Synder","publishYear":2009},
{"title":"New World (Shin-sae-gye)","author":"Lew Petersen","publishYear":1998},
{"title":"Onmyoji (Onmyoji: The Yin Yang Master)","author":"Gabi Mordue","publishYear":2003},
{"title":"Diary of a Wimpy Kid: Rodrick Rules","author":"Daron Kinman","publishYear":1986},
{"title":"Family Tree, The","author":"Celene Howis","publishYear":2012},
{"title":"See the Sea","author":"Yevette Lain","publishYear":1993},
{"title":"Pretty Maids All in a Row","author":"Charlotta Brownlow","publishYear":2012},
{"title":"Everything Relative","author":"Kathe Aldis","publishYear":2004},
{"title":"Cocoon","author":"Vally Tomkinson","publishYear":2011},
{"title":"Star Trek","author":"Elvis Pooke","publishYear":1994},
{"title":"Spring","author":"Robert Morewood","publishYear":1997},
{"title":"Reef, The","author":"Kimmie Wytchard","publishYear":1992},
{"title":"Dr. Who and the Daleks","author":"Lonnie D'Arrigo","publishYear":2002},
{"title":"Ignition","author":"Richard Stood","publishYear":1983},
{"title":"Invitation to Happiness","author":"Josey Stoner","publishYear":2010},
{"title":"Farmer & Chase","author":"Micaela Sandwick","publishYear":2012},
{"title":"Jane Austen in Manhattan","author":"Raoul Brewers","publishYear":2000},
{"title":"So Big!","author":"Jasmine De Laci","publishYear":2009},
{"title":"Man in the Middle","author":"Edward Sargison","publishYear":1995},
{"title":"Marooned in Iraq (Gomgashtei dar Aragh)","author":"Roldan Hurdiss","publishYear":2010},
{"title":"Year of Living Dangerously, The","author":"Virgil Gyurkovics","publishYear":2009},
{"title":"Wheelmen","author":"Agata Bampford","publishYear":2011},
{"title":"Griffin and Phoenix","author":"Beulah Riggs","publishYear":1990},
{"title":"Tuvalu","author":"Mariann Jermey","publishYear":2000},
{"title":"Bang Boom Bang - Ein todsicheres Ding","author":"Luz Seathwright","publishYear":2006},
{"title":"Halloween III: Season of the Witch","author":"Gwendolyn Wingeat","publishYear":1998},
{"title":"Calendar","author":"Mord Doyle","publishYear":2001},
{"title":"Mondo Topless","author":"Ferdinande Probate","publishYear":2003},
{"title":"Chhoti Si Baat","author":"Shay Burtt","publishYear":1988},
{"title":"Hottest State, The","author":"Sherilyn Brelsford","publishYear":2009},
{"title":"Evil Dead","author":"Elvyn Frazier","publishYear":2003},
{"title":"Love Before Breakfast","author":"Hyacinthe Dockwra","publishYear":1992},
{"title":"Beyond Borders","author":"Feodor Leveritt","publishYear":2006},
{"title":"Wildest Dream, The","author":"Felicity Bakes","publishYear":1993},
{"title":"Fast Runner, The (Atanarjuat)","author":"Frederique Farron","publishYear":1988},
{"title":"Mayday at 40,000 Feet!","author":"Averil Gildroy","publishYear":1998},
{"title":"Wings (Krylya)","author":"Abagael Filkin","publishYear":1996},
{"title":"Black Orpheus (Orfeu Negro)","author":"Zaneta Titchmarsh","publishYear":2007},
{"title":"Chocolate Soldier, The","author":"Zuzana Flemming","publishYear":1996},
{"title":"Patton Oswalt: Finest Hour","author":"Britney Noseworthy","publishYear":2009},
{"title":"Modris","author":"Wolfy Judkin","publishYear":2003},
{"title":"Los Angeles Plays Itself","author":"Sonnnie Murby","publishYear":1997},
{"title":"Reap the Wild Wind","author":"Jeniffer Kimbury","publishYear":2010},
{"title":"Vicky Cristina Barcelona","author":"Caprice Kornyakov","publishYear":2011},
{"title":"Business of Being Born, The","author":"Kamila Glentz","publishYear":2001},
{"title":"Joyless Street, The (Die freudlose Gasse)","author":"Romona Lawrenceson","publishYear":1991},
{"title":"Bambi Meets Godzilla","author":"Baird O'Shee","publishYear":2002},
{"title":"Alarmist, The (a.k.a. Life During Wartime)","author":"Rudd Amar","publishYear":1991},
{"title":"State of Grace","author":"Cookie Rathmell","publishYear":2010},
{"title":"Shrek 2","author":"Karee Teape","publishYear":1987},
{"title":"Laramie Project, The","author":"Granville Pinke","publishYear":1991},
{"title":"Heart of a Lion","author":"Olva Felgat","publishYear":2000},
{"title":"Asterix at the Olympic Games (Astérix aux jeux olympiques)","author":"Aristotle de Verson","publishYear":2011},
{"title":"Ranma ½: Big Trouble in Nekonron, China (Ranma ½: Chûgoku Nekonron daikessen! Okite yaburi no gekitô hen)","author":"Eric Spriggen","publishYear":1992},
{"title":"Flashpoint","author":"Dulcia Buncher","publishYear":2005},
{"title":"That Day (Ce jour-là)","author":"Lacee Penhearow","publishYear":1986},
{"title":"Strawberry Statement, The","author":"Page Yonge","publishYear":1997},
{"title":"Given Word, The (O Pagador de Promessas)","author":"Mendel Coddington","publishYear":2008},
{"title":"Remember the Day","author":"Kelsey Foss","publishYear":1992},
{"title":"Friend Is a Treasure, A (Chi Trova Un Amico, Trova un Tesoro) (Who Finds a Friend Finds a Treasure)","author":"Zebadiah Wormell","publishYear":2002},
{"title":"True Meaning of Christmas Specials, The","author":"Torrance Wastling","publishYear":1992},
{"title":"Harry Potter and the Prisoner of Azkaban","author":"Michaella Peres","publishYear":2007},
{"title":"Face to Face (Faccia a faccia)","author":"Shayne Cordle","publishYear":1994},
{"title":"Albino Farm","author":"Sollie Bradnocke","publishYear":1994}]